Metadata-Version: 1.0
Name: yasirabd-probability
Version: 0.1
Summary: Gaussian and Binomial distributions
Home-page: UNKNOWN
Author: Yasir Abdur Rohman
Author-email: sir.yasirabd@gmail.com
License: UNKNOWN
Platform: UNKNOWN
